data2db/Data2db.py
data2db/__init__.py
data2db-0.0.3.dist-info/METADATA
data2db-0.0.3.dist-info/WHEEL
data2db-0.0.3.dist-info/top_level.txt
data2db-0.0.3.dist-info/RECORD
