Metadata-Version: 2.1
Name: data2db
Version: 0.0.3
Summary: Data 2 db Migrator
Home-page: https://github.com/amankhandelwal-ideaspark/data2db
Author: Aman Khandelwal
Author-email: amanpoke@gmail.com
License: UNKNOWN
Platform: UNKNOWN
Classifier: Programming Language :: Python :: 3
Classifier: License :: OSI Approved :: MIT License
Classifier: Operating System :: OS Independent
Requires-Python: >=3.6
